LICENSE.txt
README.md
rasa/__init__.py
rasa/__main__.py
rasa/api.py
rasa/cli/__init__.py
rasa/cli/arguments/__init__.py
rasa/cli/arguments/data.py
rasa/cli/arguments/default_arguments.py
rasa/cli/arguments/run.py
rasa/cli/arguments/shell.py
rasa/cli/arguments/test.py
rasa/cli/arguments/train.py
rasa/cli/data.py
rasa/cli/initial_project/config.yml
rasa/cli/initial_project/data/nlu.yml
rasa/cli/initial_project/domain.yml
rasa/cli/run.py
rasa/cli/scaffold.py
rasa/cli/shell.py
rasa/cli/test.py
rasa/cli/train.py
rasa/cli/utils.py
rasa/constants.py
rasa/core/__init__.py
rasa/core/agent.py
rasa/core/channels/__init__.py
rasa/core/channels/channel.py
rasa/core/channels/console.py
rasa/core/constants.py
rasa/core/exceptions.py
rasa/core/lock.py
rasa/core/lock_store.py
rasa/core/processor.py
rasa/core/utils.py
rasa/engine/__init__.py
rasa/engine/caching.py
rasa/engine/constants.py
rasa/engine/exceptions.py
rasa/engine/graph.py
rasa/engine/loader.py
rasa/engine/recipes/__init__.py
rasa/engine/recipes/config_files/default_config.yml
rasa/engine/recipes/default_components.py
rasa/engine/recipes/default_recipe.py
rasa/engine/recipes/graph_recipe.py
rasa/engine/recipes/recipe.py
rasa/engine/runner/__init__.py
rasa/engine/runner/dask.py
rasa/engine/runner/interface.py
rasa/engine/storage/__init__.py
rasa/engine/storage/local_model_storage.py
rasa/engine/storage/resource.py
rasa/engine/storage/storage.py
rasa/engine/training/__init__.py
rasa/engine/training/components.py
rasa/engine/training/fingerprinting.py
rasa/engine/training/graph_trainer.py
rasa/engine/training/hooks.py
rasa/engine/validation.py
rasa/exceptions.py
rasa/graph_components/__init__.py
rasa/graph_components/converters/__init__.py
rasa/graph_components/converters/nlu_message_converter.py
rasa/graph_components/providers/__init__.py
rasa/graph_components/providers/domain_provider.py
rasa/graph_components/providers/forms_provider.py
rasa/graph_components/providers/nlu_training_data_provider.py
rasa_mini-3.8.7.dist-info/LICENSE.txt
rasa_mini-3.8.7.dist-info/METADATA
rasa_mini-3.8.7.dist-info/WHEEL
rasa_mini-3.8.7.dist-info/entry_points.txt
rasa_mini-3.8.7.dist-info/RECORD
